naverblogbacker/__init__.py
naverblogbacker/auth.py
naverblogbacker/blog.py
naverblogbacker/componentParser.py
naverblogbacker/parser.py
naverblogbacker/post.py
naverblogbacker/utils.py
naver_blog_backer-0.1.0.dist-info/LICENSE
naver_blog_backer-0.1.0.dist-info/METADATA
naver_blog_backer-0.1.0.dist-info/WHEEL
naver_blog_backer-0.1.0.dist-info/top_level.txt
naver_blog_backer-0.1.0.dist-info/RECORD
