Metadata-Version: 2.1
Name: naver-blog-backer
Version: 0.1.0
Summary: Backup your naver blog and Create backlink text file
Home-page: https://github.com/Jeongseup/naver-blog-backer
Author: Jeongseup
Author-email: thswjdtmq4@inu.ac.kr
License: GLPv3
Download-URL: https://github.com/Jeongseup/naver-blog-backer/archive/main.zip
Keywords: naver,naver blog,blog crawling,blog backup,blog backlink
Platform: UNKNOWN
Classifier: Programming Language :: Python :: 3
Classifier: License :: OSI Approved :: GNU General Public License v3 (GPLv3)
Classifier: Operating System :: OS Independent
Requires-Python: >=3.6
Requires-Dist: tqdm
Requires-Dist: beautifulsoup4
Requires-Dist: requests
Requires-Dist: pick
